[
  {
    "id": "seed-math-1",
    "topic": "一元一次方程",
    "grade": "初一",
    "difficulty": 1,
    "question": "解方程：2x + 5 = 13",
    "answer": "x = 4",
    "alternatives": [
      "4"
    ],
    "steps": [
      "移项：2x = 13 - 5",
      "合并：2x = 8",
      "x = 4"
    ],
    "socratic_hints": [
      "等式两边同时减去几？",
      "2x = 8，两边除以几？",
      "x = 4"
    ],
    "common_errors": {
      "9": "13-5=8，不是9",
      "3": "2×3+5=11≠13"
    },
    "tags": [
      "方程"
    ],
    "concept_note": "等式两边同加减同乘除，保持平衡。"
  },
  {
    "id": "seed-math-2",
    "topic": "勾股定理",
    "grade": "初二",
    "difficulty": 2,
    "question": "直角三角形两条直角边分别为 3 和 4，斜边长是多少？",
    "answer": "5",
    "alternatives": [
      "5cm"
    ],
    "steps": [
      "勾股定理：a²+b²=c²",
      "c² = 9 + 16 = 25",
      "c = 5"
    ],
    "socratic_hints": [
      "直角三角形三边满足什么定理？",
      "a²+b²=c²，代入a=3,b=4",
      "√25=5"
    ],
    "common_errors": {
      "7": "3+4=7？勾股定理是平方相加",
      "25": "25是c²，要开方"
    },
    "tags": [
      "几何"
    ],
    "concept_note": "勾股定理：a²+b²=c²。"
  },
  {
    "id": "seed-math-3",
    "topic": "概率",
    "grade": "初三",
    "difficulty": 1,
    "question": "袋中有3个红球2个蓝球，摸到红球的概率？",
    "answer": "3/5",
    "alternatives": [
      "0.6",
      "60%"
    ],
    "steps": [
      "总球数=5",
      "红球=3",
      "P=3/5"
    ],
    "socratic_hints": [
      "概率 = 符合条件数 / 总数",
      "红球3个，总共几个？",
      "3/5"
    ],
    "common_errors": {
      "2/5": "那是蓝球的概率",
      "3/2": "分子分母反了"
    },
    "tags": [
      "概率"
    ],
    "concept_note": "P(A)=发生数/总数。"
  },
  {
    "id": "seed-math-4",
    "topic": "二次函数",
    "grade": "初三",
    "difficulty": 2,
    "question": "y = x² - 2x - 3 的顶点坐标是？",
    "answer": "(1, -4)",
    "alternatives": [
      "(1,-4)"
    ],
    "steps": [
      "配方法：x²-2x+1-4",
      "(x-1)²-4",
      "顶点(1,-4)"
    ],
    "socratic_hints": [
      "顶点式y=a(x-h)²+k，h和k是什么？",
      "x=-b/(2a)=1",
      "代入得y=-4"
    ],
    "common_errors": {
      "(-1,-4)": "x-1对应x=1",
      "(1,3)": "-1-3=-4"
    },
    "tags": [
      "函数"
    ],
    "concept_note": "顶点式y=a(x-h)²+k。"
  },
  {
    "id": "seed-math-5",
    "topic": "有理数运算",
    "grade": "初一",
    "difficulty": 1,
    "question": "计算：(-2)² - 2² = ?",
    "answer": "0",
    "alternatives": [
      "0"
    ],
    "steps": [
      "(-2)²=4",
      "2²=4",
      "4-4=0"
    ],
    "socratic_hints": [
      "(-2)²底数是-2还是2？",
      "(-2)²=(-2)×(-2)=4",
      "4-4=0"
    ],
    "common_errors": {
      "-4": "(-2)²=4不是-4",
      "-8": "4-4=0"
    },
    "tags": [
      "运算"
    ],
    "concept_note": "(-a)²=a²，-a²=-(a²)。"
  },
  {
    "id": "seed-math-6",
    "topic": "实数",
    "grade": "初一",
    "difficulty": 1,
    "question": "√4 等于多少？",
    "answer": "2",
    "alternatives": [],
    "steps": [],
    "socratic_hints": [
      "平方根的定义",
      "谁的平方是4"
    ],
    "common_errors": {},
    "tags": [
      "实数",
      "初一"
    ],
    "concept_note": "√4 = 2。"
  },
  {
    "id": "seed-math-7",
    "topic": "全等三角形",
    "grade": "初二",
    "difficulty": 2,
    "question": "全等三角形的判定条件有哪些？（列出3个）",
    "answer": "SSS、SAS、ASA",
    "alternatives": [],
    "steps": [],
    "socratic_hints": [
      "边边边",
      "边角边"
    ],
    "common_errors": {},
    "tags": [
      "全等三角形",
      "初二"
    ],
    "concept_note": "SSS、SAS、ASA 判定全等。"
  },
  {
    "id": "seed-math-8",
    "topic": "一次函数",
    "grade": "初二",
    "difficulty": 2,
    "question": "一次函数 y = 2x + 1 的斜率是多少？",
    "answer": "2",
    "alternatives": [],
    "steps": [],
    "socratic_hints": [
      "斜率是x的系数",
      "2"
    ],
    "common_errors": {},
    "tags": [
      "一次函数",
      "初二"
    ],
    "concept_note": "一次函数 y=kx+b 中 k 是斜率。"
  },
  {
    "id": "seed-math-9",
    "topic": "因式分解",
    "grade": "初二",
    "difficulty": 2,
    "question": "因式分解：x² - 9",
    "answer": "(x + 3)(x - 3)",
    "alternatives": [],
    "steps": [],
    "socratic_hints": [
      "平方差公式",
      "a²-b²=(a+b)(a-b)"
    ],
    "common_errors": {},
    "tags": [
      "因式分解",
      "初二"
    ],
    "concept_note": "平方差公式 a²-b²=(a+b)(a-b)。"
  },
  {
    "id": "seed-math-10",
    "topic": "分式",
    "grade": "初二",
    "difficulty": 2,
    "question": "化简：1/2 + 1/3",
    "answer": "5/6",
    "alternatives": [],
    "steps": [],
    "socratic_hints": [
      "通分",
      "分母2和3的最小公倍数"
    ],
    "common_errors": {},
    "tags": [
      "分式",
      "初二"
    ],
    "concept_note": "分式加减先通分。"
  },
  {
    "id": "seed-math-11",
    "topic": "轴对称",
    "grade": "初二",
    "difficulty": 2,
    "question": "等腰三角形的两个底角有什么关系？",
    "answer": "相等",
    "alternatives": [],
    "steps": [],
    "socratic_hints": [
      "等腰三角形性质",
      "等边对等角"
    ],
    "common_errors": {},
    "tags": [
      "轴对称",
      "初二"
    ],
    "concept_note": "等腰三角形两底角相等。"
  },
  {
    "id": "seed-math-12",
    "topic": "数据的分析",
    "grade": "初二",
    "difficulty": 1,
    "question": "一组数据的中位数怎么找？",
    "answer": "排序后取中间的数",
    "alternatives": [],
    "steps": [],
    "socratic_hints": [
      "先排序",
      "奇数个取中间，偶数个取平均"
    ],
    "common_errors": {},
    "tags": [
      "数据的分析",
      "初二"
    ],
    "concept_note": "中位数：排序后取中间值。"
  },
  {
    "id": "seed-math-13",
    "topic": "一元二次方程",
    "grade": "初三",
    "difficulty": 2,
    "question": "解方程：x² - 4 = 0",
    "answer": "x = ±2",
    "alternatives": [],
    "steps": [],
    "socratic_hints": [
      "移项",
      "两边开平方"
    ],
    "common_errors": {},
    "tags": [
      "一元二次方程",
      "初三"
    ],
    "concept_note": "x² = a 则 x = ±√a。"
  },
  {
    "id": "seed-math-14",
    "topic": "反比例函数",
    "grade": "初三",
    "difficulty": 2,
    "question": "反比例函数 y = 6/x 的图像在哪两个象限？",
    "answer": "第一和第三象限",
    "alternatives": [],
    "steps": [],
    "socratic_hints": [
      "k>0",
      "一三象限"
    ],
    "common_errors": {},
    "tags": [
      "反比例函数",
      "初三"
    ],
    "concept_note": "k>0 时反比例函数在一三象限。"
  },
  {
    "id": "seed-math-15",
    "topic": "圆",
    "grade": "初三",
    "difficulty": 2,
    "question": "圆的周长公式是什么？",
    "answer": "C = 2πr",
    "alternatives": [],
    "steps": [],
    "socratic_hints": [
      "π约等于3.14",
      "直径×π"
    ],
    "common_errors": {},
    "tags": [
      "圆",
      "初三"
    ],
    "concept_note": "C=2πr，r为半径。"
  },
  {
    "id": "seed-math-16",
    "topic": "相似三角形",
    "grade": "初三",
    "difficulty": 3,
    "question": "两个三角形相似，对应边有什么关系？",
    "answer": "对应边成比例",
    "alternatives": [],
    "steps": [],
    "socratic_hints": [
      "相似比",
      "边长比例相同"
    ],
    "common_errors": {},
    "tags": [
      "相似三角形",
      "初三"
    ],
    "concept_note": "相似三角形对应边成比例。"
  },
  {
    "id": "seed-math-17",
    "topic": "概率",
    "grade": "初三",
    "difficulty": 2,
    "question": "一枚硬币抛两次，两次都正面朝上的概率？",
    "answer": "1/4",
    "alternatives": [],
    "steps": [],
    "socratic_hints": [
      "每次1/2",
      "相乘"
    ],
    "common_errors": {},
    "tags": [
      "概率",
      "初三"
    ],
    "concept_note": "P=1/2 × 1/2 = 1/4。"
  },
  {
    "id": "seed-math-18",
    "topic": "解直角三角形",
    "grade": "初三",
    "difficulty": 3,
    "question": "直角三角形中，已知两直角边分别为3和4，求斜边",
    "answer": "5",
    "alternatives": [],
    "steps": [],
    "socratic_hints": [
      "勾股定理",
      "3²+4²=5²"
    ],
    "common_errors": {},
    "tags": [
      "解直角三角形",
      "初三"
    ],
    "concept_note": "3-4-5直角三角形。"
  },
  {
    "id": "seed-math-19",
    "topic": "旋转",
    "grade": "初三",
    "difficulty": 2,
    "question": "图形旋转180°后与原图形重合，这是什么对称？",
    "answer": "中心对称",
    "alternatives": [],
    "steps": [],
    "socratic_hints": [
      "旋转180度",
      "中心对称"
    ],
    "common_errors": {},
    "tags": [
      "旋转",
      "初三"
    ],
    "concept_note": "旋转180°重合为中心对称。"
  },
  {
    "id": "seed-math-20",
    "topic": "三角函数",
    "grade": "初三",
    "difficulty": 3,
    "question": "sin 30° 等于多少？",
    "answer": "1/2",
    "alternatives": [],
    "steps": [],
    "socratic_hints": [
      "30-60-90三角形",
      "对边/斜边"
    ],
    "common_errors": {},
    "tags": [
      "三角函数",
      "初三"
    ],
    "concept_note": "sin 30° = 1/2。"
  },
  {
    "question": "解方程：(2x-1)/3 - (x+2)/4 = (x-1)/2 + 1",
    "answer": "x = -16",
    "alternatives": [
      "x = -16/1"
    ],
    "steps": [
      "去分母：方程两边同乘以12，得4(2x-1) - 3(x+2) = 6(x-1) + 12",
      "去括号：8x-4 -3x-6 = 6x-6+12",
      "合并同类项：5x-10 = 6x+6",
      "移项：5x-6x = 6+10 → -x=16 → x=-16"
    ],
    "socratic_hints": [
      "观察方程中各个分母，它们的最小公倍数是多少？如何去掉 分母？",
      "去分母后别忘了对每一项（包括常数项）都乘以公倍数，然后按照运算顺序化简 。",
      "移项时注意符号的变化，最后系数化1时要注意负号的处理。"
    ],
    "common_errors": {
      "x =16": "你移项时可能忘记把符号变号，注意从左边移到右边要变号。",
      "x=4": "可能在去分 母时漏乘了常数项1，记得每一项都要乘以12。",
      "x=-16/5": "可能合并同类项时系数计算错 误，检查一下5x-6x应该等于-x，而不是-5x。"
    },
    "concept_note": "解含分母的一元一次方 程，关键是去分母，注意每一项都要乘以最小公倍数，然后通过去括号、移项、合并同类项 求解。",
    "id": "math-gen-1777614536",
    "topic": "一元一次方程",
    "grade": "初三",
    "difficulty": 3,
    "tags": [
      "一元一次方程",
      "自动生成"
    ],
    "focus": "含分母的复杂一元一次方程求解（需去分母、去括号、移项合并）"
  },
  {
    "question": "小明骑自行车去图书馆，先以12km/h的速度骑了15分钟，然后因道路施工，速度降为8km/h，又骑了x分钟到达图书馆。已知全程共4.6km，求x的值。",
    "answer": "x=12",
    "alternatives": [
      "使用公式v=s/t，统一单位后求解"
    ],
    "steps": [
      "将时间统一为小时：15分钟=0.25小时，x分钟=x/60小时",
      "根据路程公式列方程：12×0.25 + 8×(x/60) = 4.6",
      "解方程：3 + (8x/60)=4.6 → 8x/60=1.6 → x=12"
    ],
    "socratic_hints": [
      "行程问题中路程、速度、时间的关系是什么？如何用公式表示？",
      "时间单位不统一时，你打算如何处理？建议都转换成小时。",
      "列出方程后，先算出第 一段路程，再解出第二段时间，注意单位对应。"
    ],
    "common_errors": {
      "x=15": "可能误将第一段路程算成3km后觉得剩余1.6km只需0.2h，但0.2h=12min，不是15min。",
      "x=0.2": "答案 未按要求以分钟为单位，应写12而不是0.2。",
      "x=24": "可能用8×0.25=2km，然后2.6/12? 实际上第二段路程应为1.6km，速度8km/h，时间0.2h=12min。"
    },
    "concept_note": "行程问题核心是路程=速度×时间，列方程时务必统一单位。",
    "id": "math-gen-1777615329",
    "topic": "一元一次方程",
    "grade": "初二",
    "difficulty": 2,
    "tags": [
      "一元一次方程",
      "自动生成"
    ],
    "focus": "一元一次方程在实际问题中的应用（行程问题）"
  },
  {
    "question": "一个长方形的长是宽的3倍，周长是48厘米。求长方形的宽是多少厘米？",
    "answer": "6",
    "alternatives": [
      "6厘米",
      "宽为6厘米"
    ],
    "steps": [
      "设宽为x厘米，则长为3x厘 米",
      "根据周长公式：2×(长+宽)=周长，列方程2×(3x + x)=48",
      "化简得8x=48，解得x=6"
    ],
    "socratic_hints": [
      "长方形的周长公式是什么？",
      "如何用含x的式子表示长和宽？",
      "根据周长公式，你能列出怎样的等式？"
    ],
    "common_errors": {
      "12": "你可能用了长+宽=周长，但实际是两倍的长+宽，纠正：周长=2×(长+宽)，所以方程应为2×(3x+x)=48",
      "6.86": "解方程时计算错误，注意合并同类项：3x+x=4x，再乘以2得8x， 不是7x",
      "8": "你可能误把周长当成了长+宽，直接用3x+x=48解得x=12，再减半得到6？或者计算8x=48解得x=8，请检查系数是否算对"
    },
    "concept_note": "解一元一次方程的关键是通过 移项和合并同类项将方程化为ax=b的形式，再两边同除以a得到解。",
    "id": "math-gen-1777615435",
    "topic": "一元一次方程",
    "grade": "初一",
    "difficulty": 1,
    "tags": [
      "一元一次方程",
      "自动生成"
    ],
    "focus": "简单一元一次方程的解（不含分母，系数为整数）"
  },
  {
    "question": "小明去文具店买了3支笔和2个本子，共花了21元。已知每支笔比每个本子贵2 元，求笔和本子的单价各是多少元？",
    "answer": "笔5元，本子3元",
    "alternatives": [
      "笔5 元/支，本子3元/本"
    ],
    "steps": [
      "设本子的单价为x元，则笔的单价为(x+2)元。",
      "根据总价列方程：3(x+2)+2x=21。",
      "解方程：3x+6+2x=21 → 5x+6=21 → 5x=15 → x=3，所以笔单价为3+2=5元。"
    ],
    "socratic_hints": [
      "如果设本子单价为x，那么笔的单价 怎样用x表示？",
      "总价21元是由哪两部分相加得到的？试着写出含x的等式。",
      "方程解完后 ，记得把x代回去验证钱数是否对得上。"
    ],
    "common_errors": {
      "设笔为x，列方程3x+2(x+2) =21": "你设笔为x是正确的，但本子比笔便宜2元，本子应该是x-2，方程应为3x+2(x-2)=21 。",
      "列方程3(x+2)+2x=21但忘记括号": "括号不能省略，因为笔的单价是(x+2)，乘以3必须 加括号，否则运算顺序会错。",
      "解方程时移项符号错误：3x+6+2x=21→5x=21-6→5x=15→x=3": "这一步没错，常见错误是写成5x=21+6导致x=5.4，注意移项要变号。"
    },
    "concept_note": "一元一次方程应用的关键是找到等量关系，设适当的未知数并正确列出方程。",
    "id": "math-gen-1777621207",
    "topic": "一元一次方程",
    "grade": "初一",
    "difficulty": 1,
    "tags": [
      "一元一次方程",
      "自动生成"
    ],
    "focus": "一元一次方程的应用（和差倍分问题，求商品单价）"
  },
  {
    "question": "一项工程，甲队单独做需要10天完成，乙队单独做需要15天完成。现两队合 作一段时间后，甲队因故离开，乙队继续单独工作5天才完成全部工程。问两队合作了几天 ？",
    "answer": "4天",
    "alternatives": [
      "4"
    ],
    "steps": [
      "设两队合作了x天，则甲队工作了x 天，乙队工作了(x+5)天。",
      "将总工作量视为单位1，甲队工作效率为1/10，乙队工作效率 为1/15。",
      "根据等量关系：甲工作量+乙工作量=1，列出方程 x/10 + (x+5)/15 = 1。",
      "解方程：去分母得3x + 2(x+5) = 30，化简得5x+10=30，解得x=4。",
      "答：两队合作了4天。"
    ],
    "socratic_hints": [
      "工程问 题中，我们常说把总工作量设为多少？",
      "甲、乙各自的工作天数与工作效率相乘，得到各 自的工作量，你能分别表达出来吗？",
      "根据“甲完成的工作量加上乙完成的工作量等于总工 作量”，试着列出一个方程。"
    ],
    "common_errors": {
      "x/10 + x/15 = 1": "你忽略了乙单独工作的5天，乙的工作天数不仅是合作天数。",
      "(x+5)/10 + x/15 = 1": "甲的工作天数应为合作天数x，而不是x+5；乙才是x+5。",
      "x/10 + (x+5)/15 = 1 解得x=5": "检查去分母步骤：3x+2(x+5)=30，合并后5x+10=30，x=4，不是5。"
    },
    "concept_ note": "工程问题的核心是将工作总量视为单位1，用工作效率乘以工作时间表示工作量，通 过各部分工作量的和等于1建立方程。",
    "id": "math-gen-1777621241",
    "topic": "一元一次方程",
    "grade": "初二",
    "difficulty": 2,
    "tags": [
      "一元一次方程",
      "自动生成"
    ],
    "concept_note": "",
    "focus": "工程问题中的一元一次方程建模"
  },
  {
    "question": "一个直角三角形的两条直角边分别长3和4，斜边长是多少？",
    "answer": "5",
    "alternatives": [
      "5",
      "6",
      "7",
      "8"
    ],
    "steps": [
      "根据勾股定理，斜边的平方等于两直角边  的平方和，即c² = a² + b²。",
      "代入a=3，b=4，得c² = 3² + 4² = 9 + 16 =             25。",
      "对25开平方，得c =                                                         5，所以斜边长为5。"
    ],
    "socratic_hints": [
      "勾股定理的公式是什么？",
      "先分别计算3的平 方和4的平方，再求和。",
      "得到平方和后，怎么得到斜边的长度？"
    ],
    "common_errors": {
      "  误加直角边": "错误地把斜边当作两直角边之和，即3+4=7，但勾股定理是平方和，不是直接 相加。",
      "忘记开平方": "计算出平方和为25后，直接回答25，忘了需要开平方才能得到边长 。",
      "平方计算错误": "比如把3²算成6或9?                                            正确是9；4²=16。仔细检查平方计算。"
    },
    "concept_note": "勾股定理：直角三角形两直角  边的平方和等于斜边的平方。",
    "id": "math-gen-1777623092",
    "topic": "勾股定理",
    "grade": "初一",
    "difficulty": 1,
    "tags": [
      "勾股定理",
      "自动生成"
    ]
  },
  {
    "question": "比较两个实数的大小：设 a = √(2024) + √(2026)，b = 2√(2025)，试比较 a 与 b 的大小。",
    "answer": "a < b",
    "alternatives": [
      "a > b",
      "a = b",
      "a <           b"
    ],
    "steps": [
      "计算 a² = (√2024+√2026)² = 2024+2026+2√(2024×2026) = 4050+2√(2024×2026)；b² = (2√2025)² = 4×2025 = 8100 = 4050+2×2025。",
      "利用平方差公式：2024×2026 = (2025-1)(2025+1)=2025²-1，所以 √(2024×2026)=√(2025²-1)。因此 a² = 4050+2√(2025²-1)。比较 a² 与 b²：因为 √(2025²-1) < 2025，所以 2√(2025²-1) < 2×2025，故 a² < b²。",
      "由于 a、b 均为正数，平方后大小关系与原数一致，所以 a < b。"
    ],
    "socratic_hints": [
      "比较两个正数的大小，我们可以考虑它们的平方。你能写出 a 和 b 的平方表达式吗？",
      "注意 a 的平方中含有根号下乘积，如何化简 2024×2026？尝试利用平方差公式。",
      "比较 a² 和 b² 时，关键是比较 2√(2024×2026) 与 2×2025 的大小。哪个更大？为什么？"
    ],
    "common_errors": {
      "a > b": "错误地认为 √2024+√2026 > 2√2025，可能直觉上觉得两个数的和大于中间数的两倍，但忽略了开方后的非线性特性，实 际上应平方后比较。",
      "a = b": "错误地假设完全平方公式导致相等，但实际计算显示 a² 小于 b²，因为 √(2025²-1) 略小于 2025。",
      "推理过程直接代入近似值": "虽然可以通过计算器得到近似值，但本题要求精确比 较，应使用代数变形而非数值近似。"
    },
    "concept_note": "比较含根号的实数大小时，常采 用平方后比较的方法，并利用完全平方公式和平方差公式进行代数变形，从而得到精确大小 关系。",
    "id": "math-gen-1777626075",
    "topic": "实数",
    "grade": "初三",
    "difficulty": 3,
    "tags": [
      "实数",
      "自动生成"
    ],
    "focus": "实数的大小比较与完全平方公式的综合应用"
  },
  {
    "question": "求√289的值",
    "answer": "17",
    "alternatives": [
      "17"
    ],
    "steps": [
      "知道16²=2 56，18²=324，介于两者之间",
      "尝试17²=289，正好是289",
      "非负数，所以算术平方根是17"
    ],
    "socratic_hints": [
      "16²和18²分别是多少？",
      "哪个整数的平方等于289？",
      "算术平方根 只能取正数，想一想答案该是几？"
    ],
    "common_errors": {
      "16": "16²=256，不等于289，再试 试",
      "18": "18²=324，比289大，而我们要找平方等于289的数",
      "-17": "算术平方根是正数， 不能为负"
    },
    "concept_note": "算术平方根是一个非负实数，其平方等于给定非负数，记作√ a（a≥0），结果≥0",
    "id": "math-gen-1777626094",
    "topic": "实数",
    "grade": "初一",
    "difficulty": 1,
    "tags": [
      "实数",
      "自动生成"
    ],
    "focus": "算术平方根的计算"
  },
  {
    "question": "已知 √13 + √5 的整数部分为 a，小数部分为 b，求 a² + ab 的值。",
    "answer": "5√13 + 5√5",
    "alternatives": [
      "5(√13+√5)"
    ],
    "steps": [
      "先估算 √13 ≈ 3.605，√5 ≈ 2.236，所以 √13+√5 ≈ 5.841，因此整数部分 a = 5",
      "小数部分 b = (√13+√5) - a = √13+√5 - 5",
      "则 a² + ab = a(a+b) = 5 × (√13+√5) = 5√13 + 5√5"
    ],
    "socratic_hints": [
      "要找整数部分，先估算两个根号的大概数值，想想它们各约多 少？",
      "通过加法估算总和，整数部分是比总和小的最大整数，你得到几？",
      "a²+ab 能不能写成 a 乘以 (a+b)？a+b 正好是原数，试试整体代入。"
    ],
    "common_errors": {
      "6": "可能将5.841四舍五入得到整数部 分6，但整数部分应取向下取整。",
      "25+5b（数值近似）": "直接代入近似小数部分计算得到 近似值，而题目要求精确值（保留根号）。",
      "a=√13, b=√5": "混淆了整数部分和小数部分，错误认为 a 和 b 分别是两个根号。"
    },
    "concept_note": "无理数的整数部分是不大于该数的最大整数，小数 部分为原数减去整数部分。",
    "id": "math-gen-1777626119",
    "topic": "实数",
    "grade": "初三",
    "difficulty": 3,
    "tags": [
      "实数",
      "自动生成"
    ],
    "focus": "无理数的整数部分与小数部分的运算"
  },
  {
    "question": "已知一次函数 y = -2x + 4，求该函数与x轴和y轴的交点坐标。",
    "answer": "x轴交点(2,0)，y轴交点(0,4)",
    "altern atives": [
      "与x轴交点为(2,0)，与y轴交点为(0,4)"
    ],
    "steps": [
      "1. 求x轴交点：令y=0，代入 y=-2x+4，得0=-2x+4；",
      "2. 解方程：-2x+4=0 → x=2，所以x轴交点坐标(2,0)；",
      "3. 求y轴交点：令x=0，代入得y=4，所以y轴交点坐标(0,4)。"
    ],
    "socratic_hints": [
      "坐标轴 上的点有什么特殊？比如x轴上的点纵坐标是多少？",
      "利用这个特征，将y=0或x=0代入函数 解析式，会得到什么方程？",
      "解出未知数后，别忘了写成有序数对的形式，哪个坐标是0？"
    ],
    "common_errors": {
      "(0,2)作为x轴交点": "你似乎把x和y坐标弄反了。x轴交点纵坐标为0 ，横坐标应为解方程得到的x值。",
      "(4,0)作为y轴交点": "y轴交点横坐标为0，纵坐标才是 方程中代入x=0得到的值，这里纵坐标应该是4。",
      "只写了一个交点(2,0)": "问题要求两个 交点，你还需要再求y轴交点。注意令x=0代入计算。",
      "得到(2,0)和(4,0)": "检查第二个： 代入x=0时y=4，不是0，所以y轴交点纵坐标是4。",
      "解方程得x=-2": "检查移项：0=-2x+4 → 2x=4 → x=2，不是-2。移项时注意符号。"
    },
    "concept_note": "一次函数与坐标轴的交点：与x轴交 点纵坐标为0，与y轴交点横坐标为0，代入解析式求解另一坐标即可。",
    "id": "math-gen-1777626178",
    "topic": "一次函数",
    "grade": "初一",
    "difficulty": 1,
    "alternatives": [],
    "tags": [
      "一次函数",
      "自动生成"
    ],
    "focus": "一次函数与坐标轴交点坐标的求解"
  },
  {
    "question": "在四边形ABCD中，AB//CD且AB=CD，E为BD的中点，连接AE、CE。求证：AE=CE 。",
    "answer": "AE=CE",
    "alternatives": [
      "AE=CE",
      "CE=AE"
    ],
    "steps": [
      "1. 因为AB//CD，所以∠ABD=∠CDB（内错角相等）。",
      "2. 因为E是BD中点，所以BE=DE。又已知AB=CD，结合∠ABD=∠CDB，根据SAS可证△ABE≌△CDE。",
      "3 . 由全等三角形对应边相等，得AE=CE。"
    ],
    "socratic_hints": [
      "题目中有平行线，平行能带 来什么角的关系？",
      "中点有什么性质？它可以提供哪两条线段相等？",
      "现在有三个条件， 能不能证明两个三角形全等？全等后能得到什么？"
    ],
    "common_errors": {
      "判断为SSA错误": "SSA不能证明全等，这里应利用平行得内错角相等，配合中点和已知边，构成SAS。",
      "错误 地认为AE=CE是因为中点对称": "中点只说明BE=DE，不代表AE=CE，需要全等证明。",
      "忽略 平行条件导致无法全等": "如果没有平行得到的角相等，只有两边相等不能证明全等。"
    },
    "c oncept_note": "利用SAS证明三角形全等，关键是找到两边及其夹角对应相等；平行线提供  等角，中点在证明中提供等边。",
    "id": "math-gen-1777626278",
    "topic": "全等三角形",
    "grade": "初二",
    "difficulty": 2,
    "tags": [
      "全等三角形",
      "自动生成"
    ],
    "concept_note": "",
    "focus": "利用SAS证明三角形全等并推导对应边相等"
  },
  {
    "question": "分解因式：x³ - 3x² + 4",
    "answer": "(x+1)(x-2)²",
    "alternatives": [
      "(x-2)(x^2-x-2)",
      "(x+2)(x^2-5x+2)",
      "( x-1)(x^2-2x-4)"
    ],
    "steps": [
      "将-3x^2拆分为-2x^2 - x^2",
      "分组为(x^3-2x^2) -         (x^2-4)",
      "提取公因式：x^2(x-2) - (x-2)(x+2)",
      "提公因式(x-2)： (x-2)(x^2 - x -    2)",
      "再分解x^2 - x - 2 = (x-2)(x+1)",
      "合并得(x-2)^2 (x+1)                        ，即(x+1)(x-2)^2"
    ],
    "socratic_hints": [
      "当x=2时多项式的值是多少？这说明什么？",
      "能 否将二次项拆成两项，使得每部分能与前后项有公因式？",
      "考虑因式定理：如果f(a)=0，  则(x-a)是因子。试求整数a。"
    ],
    "common_errors": {
      "错误1：直接利用立方差公式分解": "  此多项式不是完全立方，不能直接套用立方差。",
      "错误2：分组时符号错误导致无法提取公 因式": "分组时要仔细确定符号，可通过展开验证。",
      "错误3：因式分解不彻底": "检查二次 因式是否还能用十字相乘法分解。"
    },
    "concept_note": "因式分解需要灵活运用提公因式、  公式法、十字相乘、分组分解和拆项添项等技巧，并确保分解到不能再分为止。",
    "id": "math-gen-1777626296",
    "topic": "因式分解",
    "grade": "初三",
    "difficulty": 3,
    "tags": [
      "因式分解",
      "自动生成"
    ]
  },
  {
    "question": "因式分解：x² - 5x + 6",
    "answer": "(x-2)(x-3)",
    "alternatives": [
      "(x+2)(x+3)",
      "(x-1)(x-6)"
    ],
    "steps": [
      "找 出两个数，使它们的乘积等于常数项6，且它们的和等于一次项系数-5。",
      "这两个数分别是 -2和-3（因为(-2)×(-3)=6，(-2)+(-3)=-5）。",
      "将多项式写成 (x-2)(x-3)              的形式。"
    ],
    "socratic_hints": [
      "常数项6是正数，两个因数应该同号还是异号？",
      "一次项 系数是-5，两个因数的和是负数，说明这两个数都是负数吗？",
      "将你找到的两个数交叉相  乘再相加，结果等于-5吗？"
    ],
    "common_errors": {
      "错用加法符号": "错误地把(x-2)(x-3)展 开成x²+5x+6，注意负负得正，中间项应为-5x。",
      "因数对选择错误": "比如选了(1,6)，乘  积是6但和是7，不符合-5，应该考虑负数对。",
      "忘记检验": "写出(x+2)(x-3)后没有展开验 证，实际上得到的是x²-x-6，不是原式。"
    },
    "concept_note": "因式分解的核心是逆向运用  整式乘法，常用十字相乘法：将二次项系数和常数项分解后交叉相乘求和等于一次项系数。 ",
    "id": "math-gen-1777626342",
    "topic": "因式分解",
    "grade": "初二",
    "difficulty": 2,
    "tags": [
      "因式分解",
      "自动生成"
    ]
  },
  {
    "question": "在平行四边形ABCD中，对角线AC和BD相交于点O。已知AC=10，BD=8，AB=6， 求三角形AOB的周长。",
    "answer": "15",
    "alternatives": [
      "15cm"
    ],
    "steps": [
      "根据平行四 边形对角线互相平分的性质，AO = AC/2 = 5，BO = BD/2 = 4。",
      "三角形AOB的三边分别为AO、BO和AB，即5、4和6。",
      "周长 = 5 + 4 + 6 = 15。"
    ],
    "socratic_hints": [
      "平行四边形对角线有什么特殊关系？",
      "点O是对角线的什么点 ？",
      "知道了AO和BO的长度，加上AB，能算出周长吗？"
    ],
    "common_errors": {
      "12": "可能漏 加了边AB，只计算了AO+BO=9，或者误以为AB就是周长的一部分？但答案是15，请检查三角 形三边。",
      "20": "可能直接用了AC+BD=18，再加上AB？不对。注意三角形AOB的三边分别是A O、BO、AB，不是整个对角线。",
      "14": "计算错误：5+4+6应该等于15，而不是14。请重新计 算加法。"
    },
    "concept_note": "平行四边形对角线互相平分，即交点将每条对角线分成两段 相等线段。",
    "id": "math-gen-1777626538",
    "topic": "平行四边形",
    "grade": "初一",
    "difficulty": 1,
    "tags": [
      "平行四边形",
      "自动生成"
    ],
    "focus": "平行四边形对角线的性质（对角线互相平分）"
  },
  {
    "question": "小明买了2个苹果和3个香蕉共花18元，小红买了4个苹果和2个香蕉共花20元 。请问苹果和香蕉的单价各是多少元？",
    "answer": "苹果3元，香蕉4元",
    "alternatives": [
      "苹果3元/个，香蕉4元/个",
      "苹果单价3元，香蕉单价4元"
    ],
    "steps": [
      "设苹果单价为x元， 香蕉单价为y元，根据题意列出方程组：2x + 3y = 18，4x + 2y = 20",
      "从第一个方程用含y的式子表示x：x = (18 - 3y)/2，代入第二个方程：4*(18-3y)/2 + 2y = 20",
      "化简得36 - 6y + 2y = 20，即36 - 4y = 20，解得y = 4，再代入x表达式得x = (18-12)/2 = 3，所以苹果3元，香蕉4元"
    ],
    "socratic_hints": [
      "如果苹果单价是a元，香蕉单价是b元， 你能用a和b分别表示小明和小红的总价吗？",
      "从第一个方程把a用含b的式子表示出来，再 代入第二个方程，试试看？",
      "代入后化简得到一个关于b的一元一次方程，解出b后再求a， 检查结果是否合理。"
    ],
    "common_errors": {
      "2元/个,5元/个": "列方程时系数写反了，注意 小明买了2个苹果和3个香蕉，总价是18，正确方程是2x+3y=18，不是2x+3y=20",
      "3.5元/个, 3元/个": "代入消元时符号或计算错误，检查4*(18-3y)/2是否计算正确，注意除法要整体处 理",
      "4元/个,2元/个": "解方程组时混淆了x和y的值，建议解完后代入原方程验证总价是否 匹配"
    },
    "concept_note": "列二元一次方程组解决实际问题时，关键是找到两个等量关系， 然后用代入消元法将二元转化为一元求解。",
    "id": "math-gen-1777626700",
    "topic": "二元一次方程组",
    "grade": "初一",
    "difficulty": 1,
    "tags": [
      "二元一次方程组",
      "自动生成"
    ],
    "focus": "列二元一次方程组解商品价格问题（代入消元法）"
  },
  {
    "question": "一艘轮船在静水中的速度是水流速度的3倍。已知它顺流航行180千米比逆流 航行120千米少用1小时，求水流速度。",
    "answer": "15 km/h",
    "alternatives": [
      "10       km/h",
      "20 km/h",
      "25 km/h"
    ],
    "steps": [
      "设水流速度为x km/h，则静水速度为3x km/h，顺流速度为4x km/h，逆流速度为2x km/h。",
      "顺流时间：180/(4x) = 45/x 小时；逆流时间：120/(2x) = 60/x 小时。",
      "根据时间关系列方程：60/x - 45/x = 1。",
      "解方程得：15/x = 1，即x = 15。",
      "检验：x=15时，分母不为0，符合题意。所以水流速度为15 km/h。"
    ],
    "socratic_hints": [
      "航行问题中，顺流速度等于什么？逆流速度呢？用未知数表 示一下。",
      "尝试用未知数表达顺流和逆流的时间，注意时间差是哪个减哪个？",
      "列出方程 后，观察分母，如何去掉分母求解？"
    ],
    "common_errors": {
      "10": "静水速度与水流速度关系 搞反，误将静水速度设为x或错误计算顺逆流速度。",
      "20": "时间关系列反，把顺流比逆流 少1小时列成了多1小时。",
      "25": "解方程时计算错误，比如将15/x=1解为x=0.6，没有正确 乘除。"
    },
    "concept_note": "分式方程解决航行问题的核心是利用静水速度、水流速度合成 顺/逆流速度，通过时间差建立方程并求解。",
    "id": "math-gen-1777628794",
    "topic": "分式与分式方程",
    "grade": "初三",
    "difficulty": 3,
    "tags": [
      "分式与分式方程",
      "自动生成"
    ],
    "focus": "分式方程的应用——航行问题（静水速度、水流速度与时间关系）"
  },
  {
    "question": "解不等式 2(x-3)+5<3x-4，并在数轴上表示解集。",
    "answer": "x>3",
    "alternatives": [
      "x<3",
      "x≥3",
      "x≤3"
    ],
    "steps": [
      "去括号，得 2x-6+5<3x-4",
      "合并同类项，得 2x-1<3x-4",
      "移项，得    -1+4<3x-2x，即 3<x，所以                                                         x>3",
      "在数轴上表示为从3向右且空心圆圈"
    ],
    "socratic_hints": [
      "去括号时，2乘以(x-3)  每一项，要注意符号吗？",
      "移项时，将含x的项移到一边，常数移到另一边，需要注意什么 ？",
      "最后得到 3<x，如何写成更常见的 x>3                                          形式？"
    ],
    "common_errors": {
      "忘却括号乘法": "忘记乘以2，写成2x-3+5<3x-4，导致错误。 ",
      "移项不变号": "直接写成2x-1-3x<-4，忘记移动的项要变号。",
      "不等号方向错误": "最后 得到3<x，错误地写成x<3，忽略了不等号方向随移项而改变。"
    },
    "concept_note": "解一元  一次不等式时，步骤与解方程相同，但要注意不等号方向：两边同乘除负数时变号，移项时 变号但不等号方向不变。",
    "id": "math-gen-1777628861",
    "topic": "不等式",
    "grade": "初二",
    "difficulty": 2,
    "tags": [
      "不等式",
      "自动生成"
    ]
  },
  {
    "question": "某班7名同学在一次数学测验中的成绩（单位：分）分别为：85, 90, 78, 92, 85, 88, 95。求这组数据的平均数和中位数。",
    "answer": "平均数为87.57（或613/7），中位数为88 。",
    "alternatives": [
      "87.6和88"
    ],
    "steps": [
      "将所有成绩相加：85+90+78+92+85+88+95=6 13",
      "用总和除以人数：613÷7≈87.57，得到平均数",
      "将成绩从小到大排序：78,85,85,88,9 0,92,95，中间第4个数是88，即中位数"
    ],
    "socratic_hints": [
      "你记得平均数是怎么算出来 的吗？需要总和除以什么？",
      "中位数需要先把数据按什么顺序排列？",
      "当数据个数是奇数 时，中位数是排序后第几个位置的数？"
    ],
    "common_errors": {
      "613": "只加出了总和，忘了 除以人数",
      "85": "误将众数85当作中位数，没有排序",
      "90或92": "排序错误取了第5或第6个 数，或者没排序直接取中间值"
    },
    "concept_note": "平均数是一组数据的总和除以个数，反 映整体水平；中位数是排序后位于中间的数，反映中间水平，不受极端值影响。",
    "id": "math-gen-1777628934",
    "topic": "数据的分析",
    "grade": "初一",
    "difficulty": 1,
    "tags": [
      "数据的分析",
      "自动生成"
    ],
    "focus": "平均数和中位数的计算"
  }
]